proface/abaqus/preprocessor/__init__.py
proface/abaqus/preprocessor/_version.py
proface/abaqus/preprocessor/translator.py
proface_abaqus_pre-0.1.0.dist-info/METADATA
proface_abaqus_pre-0.1.0.dist-info/WHEEL
proface_abaqus_pre-0.1.0.dist-info/entry_points.txt
proface_abaqus_pre-0.1.0.dist-info/RECORD
