Metadata-Version: 2.4
Name: proface-abaqus-pre
Version: 0.1.0
Summary: Abaqus to ProFACE preprocessor
Project-URL: documentation, https://github.com/ProFACE-dev/proface-abaqus-pre#proface-abaqus-pre
Project-URL: issues, https://github.com/ProFACE-dev/proface-abaqus-pre/issues
Project-URL: source, https://github.com/ProFACE-dev/proface-abaqus-pre
Author-email: Stefano Miccoli <stefano.miccoli@polimi.it>
License-Expression: MIT
Classifier: Development Status :: 3 - Alpha
Classifier: Environment :: Console
Classifier: Programming Language :: Python
Classifier: Programming Language :: Python :: 3.12
Classifier: Programming Language :: Python :: 3.13
Classifier: Programming Language :: Python :: Implementation :: CPython
Requires-Python: >=3.12
Requires-Dist: h5py>=3.13.0
Requires-Dist: numpy>=2.0
Requires-Dist: proface-pre>=0.2.0
Requires-Dist: suanpan-abaqus~=0.1.0
